{
  "$schema": "https://json-schema.org/draft/2020-12/schema",
  "$id": "https://nexus/manifest_schema.json",
  "title": "Nexus extension manifest",
  "description": "Schema for the manifest.json document that declares a Nexus extension's identity and all surfaces it contributes to the forum. Mirrors the validation behaviour of Nexus.Extensions.ManifestSchema in the Elixir codebase.",
  "type": "object",
  "required": ["manifest_version", "name", "slug", "version", "module"],
  "additionalProperties": true,

  "properties": {
    "manifest_version": {
      "description": "Manifest schema version. Currently only version 2 is supported.",
      "type": "integer",
      "enum": [2]
    },

    "name": {
      "description": "Human-readable name shown to admins and in the extension store.",
      "type": "string",
      "minLength": 1
    },
    "slug": {
      "description": "Lowercase, URL-safe identifier. Used as the extension's namespace under /ext/<slug>.",
      "type": "string",
      "pattern": "^[a-z0-9-]+$"
    },
    "version": {
      "description": "Semantic version of this manifest (e.g. \"1.0.0\" or \"1.0.0-beta.1\").",
      "type": "string",
      "pattern": "^\\d+\\.\\d+\\.\\d+(?:[-+][0-9A-Za-z\\-.]+)?$"
    },

    "description": { "type": "string" },
    "author":      { "type": "string" },

    "homepage":   { "type": "string", "format": "uri-reference" },
    "repository": { "type": "string", "format": "uri-reference" },
    "license":    { "type": "string" },
    "tags":       { "type": "array", "items": { "type": "string" } },
    "compatible_with": {
      "description": "Semver-style constraint on the Nexus version this extension supports (e.g. \"^4.0\").",
      "type": "string"
    },

    "logo_url":   { "type": "string" },
    "banner_url": { "type": "string" },

    "module": {
      "description": "The Elixir module name implementing Nexus.Extensions.Behaviour (e.g. \"Gamepedia\" or \"Gamepedia.Extension\").",
      "type": "string",
      "pattern": "^[A-Z][A-Za-z0-9_.]*$"
    },
    "js_bundle": {
      "description": "Relative path to the JS bundle within the extension's priv/static directory (e.g. \"gamepedia.js\"). Must not be absolute or contain '..'.",
      "type": ["string", "null"]
    },

    "settings_schema": {
      "description": "Declarative schema for the admin settings form. See https://docs.nexusprism.org/extensions/building/",
      "type": "object"
    },
    "settings_tabs": {
      "description": "Optional tab grouping for the admin settings form.",
      "type": "array"
    },

    "capabilities": {
      "description": "Capabilities this extension declares it needs. Enforcement is planned for a future Nexus version; declared values are advisory for now.",
      "type": "array",
      "items": { "type": "string" }
    },
    "side_data": {
      "description": "Entity attachments this extension contributes. Each entry declares: I attach data of `kind` to entities of `entity`. The compose flow dispatches matching attachments to this extension's persist_attachment/3 callback at create time. Extensions are responsible for cleaning up linked rows when entities are deleted, typically by subscribing to the corresponding *_deleted hook event.",
      "type": "array",
      "items": {
        "type": "object",
        "required": ["entity", "kind"],
        "properties": {
          "entity": {
            "type": "string",
            "enum": ["post", "reply", "user"],
            "description": "The core entity type this side-data attaches to."
          },
          "kind": {
            "type": "string",
            "minLength": 1,
            "description": "A string identifier for this kind of attachment. Extensions should namespace their kinds (e.g. \"gamepedia_game_link\") to avoid collisions with other extensions."
          }
        }
      }
    },

    "hooks": {
      "description": "Hook event subscriptions for this extension's handle_event/3 callback. Each entry is either the event name as a string (default priority 50) or an object with explicit priority. Handlers run in priority order at dispatch time, lowest first; within the same priority, order is undefined.",
      "type": "array",
      "items": {
        "oneOf": [
          {
            "type": "string",
            "enum": [
              "post_created", "post_updated", "post_deleted",
              "reply_created", "reply_deleted",
              "reaction_added", "reaction_removed",
              "report_created", "report_resolved",
              "user_registered", "user_login"
            ]
          },
          {
            "type": "object",
            "required": ["event"],
            "properties": {
              "event": {
                "type": "string",
                "enum": [
                  "post_created", "post_updated", "post_deleted",
                  "reply_created", "reply_deleted",
                  "reaction_added", "reaction_removed",
                  "report_created", "report_resolved",
                  "user_registered", "user_login"
                ]
              },
              "priority": {
                "type": "number",
                "description": "Lower runs first. Defaults to 50. Handlers within the same priority have undefined order."
              }
            }
          }
        ]
      }
    },

    "slots": {
      "description": "UI slot names this extension's JS bundle registers components into.",
      "type": "array",
      "items": {
        "type": "string",
        "enum": [
          "feed_top", "feed_bottom", "feed_sidebar",
          "post_header", "post_footer", "post_sidebar",
          "reply_footer",
          "profile_header", "profile_sidebar",
          "nav_top", "nav_bottom",
          "admin_sidebar"
        ]
      }
    },

    "routes": {
      "description": "SPA routes this extension owns. Paths are relative to /ext/<slug>; do not include /ext/ yourself.",
      "type": "array",
      "items": {
        "type": "object",
        "required": ["path"],
        "additionalProperties": false,
        "properties": {
          "path": {
            "type": "string",
            "pattern": "^/(?!ext/)",
            "description": "Path relative to /ext/<slug>, must start with /."
          },
          "title": {
            "type": ["string", "null"],
            "description": "Title shown in the page back-header. Optional."
          }
        }
      }
    },

    "admin_panel": {
      "description": "Adds an entry to the admin sidebar under 'installed extensions'. The component is registered via the JS bundle.",
      "type": ["object", "null"],
      "required": ["label", "icon"],
      "properties": {
        "label": { "type": "string" },
        "icon":  { "type": "string", "description": "Font Awesome solid icon class, e.g. \"fa-gamepad\"." }
      }
    },

    "explore": {
      "description": "Adds an entry to the left sidebar Explore section.",
      "type": ["object", "null"],
      "required": ["label", "icon"],
      "properties": {
        "label": { "type": "string" },
        "icon":  { "type": "string" },
        "path":  {
          "type": "string",
          "pattern": "^/(?!ext/)",
          "description": "Path within your extension namespace (defaults to /). The Explore item links to /ext/<slug><path>."
        }
      }
    },

    "digest_sections": {
      "description": "Sections this extension contributes to the digest email. Each section's data is produced by handle_digest_section/3.",
      "type": "array",
      "items": {
        "type": "object",
        "required": ["key", "label"],
        "properties": {
          "key":   { "type": "string" },
          "label": { "type": "string" },
          "icon":  { "type": "string" },
          "enabled_by_default": { "type": "boolean" }
        }
      }
    },

    "right_widgets": {
      "description": "Right sidebar widgets this extension's JS bundle registers.",
      "type": "array",
      "items": {
        "type": "object",
        "required": ["id", "label"],
        "properties": {
          "id":    { "type": "string" },
          "label": { "type": "string" },
          "priority": { "type": "number" },
          "scope": {
            "description": "Where the widget appears. Defaults to \"extension\".",
            "oneOf": [
              { "type": "string", "enum": ["extension", "global"] },
              {
                "type": "object",
                "additionalProperties": false,
                "properties": {
                  "path": {
                    "oneOf": [
                      { "type": "string", "pattern": "^/(?!ext/)" },
                      { "type": "array", "items": { "type": "string", "pattern": "^/(?!ext/)" } }
                    ]
                  }
                }
              },
              {
                "type": "object",
                "additionalProperties": false,
                "properties": {
                  "corePages": {
                    "type": "array",
                    "items": {
                      "type": "string",
                      "enum": [
                        "feed", "post", "profile", "members", "leaderboard",
                        "badges", "search", "notifications", "messages",
                        "saved", "drafts"
                      ]
                    }
                  }
                }
              }
            ]
          }
        }
      }
    },

    "toolbar_buttons": {
      "description": "Composer toolbar buttons this extension's JS bundle registers.",
      "type": "array",
      "items": {
        "type": "object",
        "required": ["id", "icon", "tip"],
        "properties": {
          "id":   { "type": "string" },
          "icon": {
            "type": "string",
            "description": "Full Font Awesome class with style prefix (e.g. \"fa-solid fa-gamepad\")."
          },
          "tip":   { "type": "string" },
          "scope": { "type": "string", "enum": ["both", "posts", "replies"] },
          "priority": { "type": "number" }
        }
      }
    },

    "profile_tabs": {
      "description": "Tabs this extension's JS bundle registers on /profile/:username pages. Each tab has a stable id (used for deep-linking and the initialTab navigation prop), a label shown in the tab bar, and optional icon/visibility/priority. The extension's component is registered separately via the JS bundle's NE.registerProfileTab call.",
      "type": "array",
      "items": {
        "type": "object",
        "required": ["id", "label"],
        "properties": {
          "id":    { "type": "string", "description": "Stable identifier for this tab. Used as the URL fragment for deep-linking and must match the id passed to registerProfileTab." },
          "label": { "type": "string", "description": "Display label in the tab bar." },
          "icon":  { "type": "string", "description": "Optional Font Awesome solid icon class (e.g. \"fa-trophy\"). When omitted, only the label shows." },
          "visibility": {
            "type": "string",
            "enum": ["always", "own_only"],
            "description": "When the tab button appears. \"always\" (default) shows the tab to anyone viewing the profile; \"own_only\" shows the tab only when the viewer is the profile owner. This is a UX hint only — it gates the button, not access to underlying data. Enforce access control server-side if needed."
          },
          "priority": { "type": "number", "description": "Lower values render earlier in the tab bar. Defaults to 50." }
        }
      }
    },

    "notification_types": {
      "description": "Notification types this extension sends. Each declared type appears as a row in the user's notification preferences page (grouped under a per-extension header) and is used to validate notification data payloads at send time. Send notifications matching these keys via Nexus.Notifications.notify_extension/3 server-side, or POST /api/v1/notifications/extension from the JS bundle.",
      "type": "array",
      "items": {
        "type": "object",
        "required": ["key", "label", "description", "channels"],
        "properties": {
          "key":         { "type": "string", "pattern": "^[a-z][a-z0-9_]*$", "maxLength": 64, "description": "Stable identifier sent as data.ext_type. Should be prefixed with the extension slug for clarity (e.g. \"gamepedia_new_game\")." },
          "label":       { "type": "string", "maxLength": 64, "description": "Short user-facing name shown in the preferences row (e.g. \"New game added\")." },
          "description": { "type": "string", "maxLength": 200, "description": "Sublabel shown below the label in preferences, explaining what triggers this notification." },
          "icon":        { "type": "string", "description": "Optional Font Awesome solid icon class. Defaults to fa-bell." },
          "channels":    {
            "type": "array",
            "items": { "type": "string", "enum": ["web", "email", "push"] },
            "minItems": 1,
            "description": "Which delivery channels this notification type supports. The user can independently toggle each. Channels not in this list render as a greyed-out '—' in the preferences row and never deliver."
          },
          "default_preferences": {
            "type": "object",
            "description": "Per-channel default toggle state for new users. Keys must be channels declared above; values are booleans. Defaults to web=true, others=false.",
            "additionalProperties": { "type": "boolean" }
          },
          "payload_schema": {
            "type": "object",
            "description": "Optional contract for the data payload at send time. Keys are field names; values are human-readable descriptions of what each field is for. When present, Nexus validates outgoing notifications of this type against the schema and rejects ones missing declared fields.",
            "additionalProperties": { "type": "string" }
          }
        }
      }
    },
    "permissions": {
      "description": "Permission gates this extension enforces, surfaced on the admin Permissions page under a per-extension header. Each entry declares a gate by key and label; the admin sets the minimum role required. Check gates server-side with Nexus.Extensions.Permissions.check/3. Values are stored in the extension's settings map, so permission keys must not collide with settings_schema keys.",
      "type": "array",
      "items": {
        "type": "object",
        "required": ["key", "label"],
        "properties": {
          "key":     { "type": "string", "pattern": "^[a-z0-9_]+$", "maxLength": 64, "description": "Stable identifier used in Permissions.check/3 calls. Lowercase alphanumeric and underscores only. Must not collide with any settings_schema key." },
          "label":   { "type": "string", "maxLength": 120, "description": "Human-readable description of what this gate controls, shown as the row label on the Permissions page (e.g. \"Can view the gallery\")." },
          "default": {
            "type": "string",
            "enum": ["everyone", "member", "moderator", "admin"],
            "description": "The permission level applied before an admin has explicitly saved a value. 'everyone' includes guests (subject to the site-wide guest_browsing setting). Defaults to 'member' if omitted."
          }
        }
      }
    }
  }
}
